{"v":"5.7.1","fr":30,"ip":0,"op":90,"w":306,"h":300,"nm":"Artboard 3","ddd":0,"assets":[],"layers":[{"ddd":0,"ind":1,"ty":4,"nm":"Scan_light 2","parent":4,"sr":1,"ks":{"o":{"a":1,"k":[{"i":{"x":[0.667],"y":[1]},"o":{"x":[0.333],"y":[0]},"t":29,"s":[60]},{"t":53,"s":[0]}],"ix":11},"r":{"a":0,"k":180,"ix":10},"p":{"a":0,"k":[2,-12,0],"ix":2},"a":{"a":0,"k":[-3.5,-79,0],"ix":1},"s":{"a":1,"k":[{"i":{"x":[0.667,0.667,0.667],"y":[1,1,1]},"o":{"x":[0.333,0.333,0.333],"y":[0,0,0]},"t":29,"s":[100,0,100]},{"i":{"x":[0.667,0.667,0.667],"y":[1,1,1]},"o":{"x":[0.333,0.333,0.333],"y":[0,0,0]},"t":34,"s":[100,203.226,100]},{"i":{"x":[0.667,0.667,0.667],"y":[1,1,1]},"o":{"x":[0.333,0.333,0.333],"y":[0,0,0]},"t":47,"s":[100,203.226,100]},{"t":56,"s":[100,0,100]}],"ix":6}},"ao":0,"shapes":[{"ty":"gr","it":[{"ind":0,"ty":"sh","ix":1,"ks":{"a":0,"k":{"i":[[0,0],[0,0],[0,0],[0,0]],"o":[[0,0],[0,0],[0,0],[0,0]],"v":[[84.5,-79],[-89,-79],[-70,-61.04],[62,-61.04]],"c":true},"ix":2},"nm":"Path 1","mn":"ADBE Vector Shape - Group","hd":false},{"ty":"gf","o":{"a":0,"k":100,"ix":10},"r":1,"bm":0,"g":{"p":3,"k":{"a":0,"k":[0,1,1,1,0.5,0.807843137254902,0.807843137254902,0.807843137254902,1,0.6941176470588235,0.6941176470588235,0.6941176470588235],"ix":9}},"s":{"a":0,"k":[-2.819,-63.45],"ix":5},"e":{"a":0,"k":[-2.703,-78.362],"ix":6},"t":1,"nm":"Gradient Fill 1","mn":"ADBE Vector Graphic - G-Fill","hd":false},{"ty":"tr","p":{"a":0,"k":[0,0],"ix":2},"a":{"a":0,"k":[0,0],"ix":1},"s":{"a":0,"k":[100,100],"ix":3},"r":{"a":0,"k":0,"ix":6},"o":{"a":0,"k":100,"ix":7},"sk":{"a":0,"k":0,"ix":4},"sa":{"a":0,"k":0,"ix":5},"nm":"Transform"}],"nm":"Shape 1","np":3,"cix":2,"bm":0,"ix":1,"mn":"ADBE Vector Group","hd":false}],"ip":29,"op":119,"st":29,"bm":0},{"ddd":0,"ind":2,"ty":4,"nm":"Scan_light","parent":4,"sr":1,"ks":{"o":{"a":1,"k":[{"i":{"x":[0.667],"y":[1]},"o":{"x":[0.333],"y":[0]},"t":0,"s":[60]},{"t":24,"s":[0]}],"ix":11},"r":{"a":0,"k":0,"ix":10},"p":{"a":0,"k":[-0.5,12,0],"ix":2},"a":{"a":0,"k":[-3.5,-79,0],"ix":1},"s":{"a":1,"k":[{"i":{"x":[0.667,0.667,0.667],"y":[1,1,1]},"o":{"x":[0.333,0.333,0.333],"y":[0,0,0]},"t":0,"s":[100,0,100]},{"i":{"x":[0.667,0.667,0.667],"y":[1,1,1]},"o":{"x":[0.333,0.333,0.333],"y":[0,0,0]},"t":5,"s":[100,203.226,100]},{"i":{"x":[0.667,0.667,0.667],"y":[1,1,1]},"o":{"x":[0.333,0.333,0.333],"y":[0,0,0]},"t":16,"s":[100,203.226,100]},{"t":27,"s":[100,0,100]}],"ix":6}},"ao":0,"shapes":[{"ty":"gr","it":[{"ind":0,"ty":"sh","ix":1,"ks":{"a":0,"k":{"i":[[0,0],[0,0],[0,0],[0,0]],"o":[[0,0],[0,0],[0,0],[0,0]],"v":[[84.5,-79],[-89,-79],[-65.5,-60.056],[66,-60.548]],"c":true},"ix":2},"nm":"Path 1","mn":"ADBE Vector Shape - Group","hd":false},{"ty":"gf","o":{"a":0,"k":100,"ix":10},"r":1,"bm":0,"g":{"p":3,"k":{"a":0,"k":[0,1,1,1,0.5,0.807843137254902,0.807843137254902,0.807843137254902,1,0.6941176470588235,0.6941176470588235,0.6941176470588235],"ix":9}},"s":{"a":0,"k":[-2.819,-63.45],"ix":5},"e":{"a":0,"k":[-2.703,-78.362],"ix":6},"t":1,"nm":"Gradient Fill 1","mn":"ADBE Vector Graphic - G-Fill","hd":false},{"ty":"tr","p":{"a":0,"k":[0,0],"ix":2},"a":{"a":0,"k":[0,0],"ix":1},"s":{"a":0,"k":[100,100],"ix":3},"r":{"a":0,"k":0,"ix":6},"o":{"a":0,"k":100,"ix":7},"sk":{"a":0,"k":0,"ix":4},"sa":{"a":0,"k":0,"ix":5},"nm":"Transform"}],"nm":"Shape 1","np":3,"cix":2,"bm":0,"ix":1,"mn":"ADBE Vector Group","hd":false}],"ip":0,"op":90,"st":0,"bm":0},{"ddd":0,"ind":3,"ty":4,"nm":"Shape","sr":1,"ks":{"o":{"a":0,"k":100,"ix":11},"r":{"a":0,"k":0,"ix":10},"p":{"a":0,"k":[150,147,0],"ix":2},"a":{"a":0,"k":[0,0,0],"ix":1},"s":{"a":0,"k":[100,100,100],"ix":6}},"ao":0,"shapes":[{"ty":"gr","it":[{"ind":0,"ty":"sh","ix":1,"ks":{"a":0,"k":{"i":[[-1.44,0],[-0.09,-1.41],[0,0],[0,0],[0,0],[-2.21,-0.11],[0,0],[0,0],[0,0],[0,-1.43],[1.42,-0.09],[0,0],[0,0],[0,0],[0.15,5.1],[0,0],[0,0],[0,0]],"o":[[1.45,0],[0,0],[0,0],[0,0],[0.09,2.19],[0,0],[0,0],[0,0],[1.43,0.07],[0,1.43],[0,0],[0,0],[0,0],[-5.16,-0.12],[0,0],[0,0],[0,0],[0.08,-1.41]],"v":[[-40.29,23.275],[-37.58,25.795],[-37.57,25.965],[-37.57,33.385],[-37.57,33.555],[-33.51,37.615],[-33.31,37.615],[-25.99,37.615],[-25.84,37.625],[-23.28,40.305],[-25.82,42.995],[-25.99,42.995],[-33.31,42.995],[-33.54,42.995],[-43,33.665],[-43,33.385],[-43,25.965],[-43,25.815]],"c":true},"ix":2},"nm":"Path 1","mn":"ADBE Vector Shape - Group","hd":false},{"ind":1,"ty":"sh","ix":2,"ks":{"a":0,"k":{"i":[[-1.5,0],[-0.08,-1.41],[0,0],[0,0],[5.24,-0.12],[0,0],[0,0],[0,1.49],[-1.43,0.07],[0,0],[0,0],[-0.09,2.26],[0,0],[0,0]],"o":[[1.45,0],[0,0],[0,0],[0,5.23],[0,0],[0,0],[-1.49,0],[0,-1.43],[0,0],[0,0],[2.3,0],[0,0],[0,0],[0,-1.49]],"v":[[39.496,23.275],[42.206,25.815],[42.206,25.965],[42.206,33.385],[32.756,42.995],[32.516,42.995],[25.196,42.995],[22.486,40.305],[25.056,37.625],[25.196,37.615],[32.516,37.615],[36.776,33.555],[36.786,33.385],[36.786,25.965]],"c":true},"ix":2},"nm":"Path 2","mn":"ADBE Vector Shape - Group","hd":false},{"ind":2,"ty":"sh","ix":3,"ks":{"a":0,"k":{"i":[[0,0],[0,-1.49],[1.43,-0.08],[0,0],[0,0],[0.09,-2.26],[0,0],[0,0],[1.5,0],[0.08,1.42],[0,0],[0,0],[-5.25,0.13],[0,0]],"o":[[1.5,0],[0,1.44],[0,0],[0,0],[-2.29,0],[0,0],[0,0],[0,1.49],[-1.44,0],[0,0],[0,0],[0,-5.23],[0,0],[0,0]],"v":[[-25.201,-43],[-22.491,-40.31],[-25.051,-37.62],[-25.201,-37.62],[-32.521,-37.62],[-36.781,-33.56],[-36.781,-33.39],[-36.781,-25.97],[-39.501,-23.28],[-42.211,-25.82],[-42.211,-25.97],[-42.211,-33.39],[-32.751,-43],[-32.521,-43]],"c":true},"ix":2},"nm":"Path 3","mn":"ADBE Vector Shape - Group","hd":false},{"ind":3,"ty":"sh","ix":4,"ks":{"a":0,"k":{"i":[[0,0],[0,0],[-0.14,-5.11],[0,0],[0,0],[0,0],[1.45,0],[0.09,1.41],[0,0],[0,0],[0,0],[2.2,0.1],[0,0],[0,0],[0,0],[0,1.44],[-1.42,0.08],[0,0]],"o":[[0,0],[5.15,0.13],[0,0],[0,0],[0,0],[-0.08,1.42],[-1.44,0],[0,0],[0,0],[0,0],[-0.08,-2.19],[0,0],[0,0],[0,0],[-1.43,-0.08],[0,-1.43],[0,0],[0,0]],"v":[[33.305,-43],[33.545,-43],[42.995,-33.66],[42.995,-33.39],[42.995,-25.97],[42.995,-25.82],[40.285,-23.28],[37.575,-25.8],[37.575,-25.97],[37.575,-33.39],[37.565,-33.56],[33.515,-37.61],[33.305,-37.62],[25.985,-37.62],[25.845,-37.62],[23.275,-40.31],[25.815,-42.99],[25.985,-43]],"c":true},"ix":2},"nm":"Path 4","mn":"ADBE Vector Shape - Group","hd":false},{"ty":"mm","mm":1,"nm":"Merge Paths 1","mn":"ADBE Vector Filter - Merge","hd":false},{"ty":"fl","c":{"a":0,"k":[0.09411764705882353,0.09411764705882353,0.09411764705882353,1],"ix":4},"o":{"a":0,"k":100,"ix":5},"r":1,"bm":0,"nm":"Fill 1","mn":"ADBE Vector Graphic - Fill","hd":false},{"ty":"tr","p":{"a":0,"k":[0,0],"ix":2},"a":{"a":0,"k":[0,0],"ix":1},"s":{"a":0,"k":[300,300],"ix":3},"r":{"a":0,"k":0,"ix":6},"o":{"a":0,"k":100,"ix":7},"sk":{"a":0,"k":0,"ix":4},"sa":{"a":0,"k":0,"ix":5},"nm":"Transform"}],"nm":"Shape","np":6,"cix":2,"bm":0,"ix":1,"mn":"ADBE Vector Group","hd":false}],"ip":0,"op":90,"st":0,"bm":0},{"ddd":0,"ind":4,"ty":4,"nm":" Palka_Positiom","sr":1,"ks":{"o":{"a":0,"k":100,"ix":11},"r":{"a":0,"k":0,"ix":10},"p":{"a":1,"k":[{"i":{"x":0.667,"y":1},"o":{"x":0.333,"y":0},"t":0,"s":[150,64,0],"to":[0,0,0],"ti":[0,0,0]},{"i":{"x":0.667,"y":0.667},"o":{"x":0.333,"y":0.333},"t":30,"s":[150,227,0],"to":[0,0,0],"ti":[0,0,0]},{"i":{"x":0.667,"y":1},"o":{"x":0.333,"y":0},"t":32,"s":[150,227,0],"to":[0,0,0],"ti":[0,0,0]},{"t":60,"s":[150,63,0]}],"ix":2},"a":{"a":0,"k":[0,0,0],"ix":1},"s":{"a":0,"k":[100,100,100],"ix":6}},"ao":0,"shapes":[{"ty":"gr","it":[{"ty":"rc","d":1,"s":{"a":0,"k":[60,6],"ix":2},"p":{"a":0,"k":[0,0],"ix":3},"r":{"a":0,"k":3,"ix":4},"nm":"Rectangle Path 1","mn":"ADBE Vector Shape - Rect","hd":false},{"ty":"gf","o":{"a":0,"k":100,"ix":10},"r":1,"bm":0,"g":{"p":5,"k":{"a":0,"k":[0,1,0.9215686274509803,0,0.152,1,0.9215686274509803,0,0.304,1,0.9215686274509803,0,0.652,1,0.9215686274509803,0,1,1,0.9215686274509803,0],"ix":9}},"s":{"a":0,"k":[0,-3],"ix":5},"e":{"a":0,"k":[0,3],"ix":6},"t":1,"nm":"Gradient Fill 1","mn":"ADBE Vector Graphic - G-Fill","hd":false},{"ty":"tr","p":{"a":0,"k":[0,0],"ix":2},"a":{"a":0,"k":[0,0],"ix":1},"s":{"a":0,"k":[300,300],"ix":3},"r":{"a":0,"k":0,"ix":6},"o":{"a":0,"k":100,"ix":7},"sk":{"a":0,"k":0,"ix":4},"sa":{"a":0,"k":0,"ix":5},"nm":"Transform"}],"nm":"Rectangle","np":2,"cix":2,"bm":0,"ix":1,"mn":"ADBE Vector Group","hd":false}],"ip":0,"op":90,"st":0,"bm":0},{"ddd":0,"ind":5,"ty":4,"nm":"Path","sr":1,"ks":{"o":{"a":0,"k":100,"ix":11},"r":{"a":0,"k":0,"ix":10},"p":{"a":0,"k":[179,135,0],"ix":2},"a":{"a":0,"k":[0,0,0],"ix":1},"s":{"a":0,"k":[100,100,100],"ix":6}},"ao":0,"shapes":[{"ty":"gr","it":[{"ind":0,"ty":"sh","ix":1,"ks":{"a":0,"k":{"i":[[-1.84,0],[0,-1.84],[1.84,0],[0,1.84]],"o":[[1.84,0],[0,1.84],[-1.84,0],[0,-1.84]],"v":[[-0.003,-3.333],[3.337,-0.003],[-0.003,3.337],[-3.333,-0.003]],"c":true},"ix":2},"nm":"Path 1","mn":"ADBE Vector Shape - Group","hd":false},{"ty":"fl","c":{"a":0,"k":[0,0,0,1],"ix":4},"o":{"a":0,"k":100,"ix":5},"r":1,"bm":0,"nm":"Fill 1","mn":"ADBE Vector Graphic - Fill","hd":false},{"ty":"tr","p":{"a":0,"k":[0,0],"ix":2},"a":{"a":0,"k":[0,0],"ix":1},"s":{"a":0,"k":[300,300],"ix":3},"r":{"a":0,"k":0,"ix":6},"o":{"a":0,"k":100,"ix":7},"sk":{"a":0,"k":0,"ix":4},"sa":{"a":0,"k":0,"ix":5},"nm":"Transform"}],"nm":"Path","np":2,"cix":2,"bm":0,"ix":1,"mn":"ADBE Vector Group","hd":false}],"ip":90,"op":90,"st":0,"bm":0,"hidden":0},{"ddd":0,"ind":6,"ty":4,"nm":"Path","sr":1,"ks":{"o":{"a":0,"k":100,"ix":11},"r":{"a":0,"k":0,"ix":10},"p":{"a":0,"k":[127,135,0],"ix":2},"a":{"a":0,"k":[0,0,0],"ix":1},"s":{"a":0,"k":[100,100,100],"ix":6}},"ao":0,"shapes":[{"ty":"gr","it":[{"ind":0,"ty":"sh","ix":1,"ks":{"a":0,"k":{"i":[[-1.84,0],[0,-1.84],[1.84,0],[0,1.84]],"o":[[1.84,0],[0,1.84],[-1.84,0],[0,-1.84]],"v":[[-0.003,-3.333],[3.337,-0.003],[-0.003,3.337],[-3.333,-0.003]],"c":true},"ix":2},"nm":"Path 1","mn":"ADBE Vector Shape - Group","hd":false},{"ty":"fl","c":{"a":0,"k":[0,0,0,1],"ix":4},"o":{"a":0,"k":100,"ix":5},"r":1,"bm":0,"nm":"Fill 1","mn":"ADBE Vector Graphic - Fill","hd":false},{"ty":"tr","p":{"a":0,"k":[0,0],"ix":2},"a":{"a":0,"k":[0,0],"ix":1},"s":{"a":0,"k":[300,300],"ix":3},"r":{"a":0,"k":0,"ix":6},"o":{"a":0,"k":100,"ix":7},"sk":{"a":0,"k":0,"ix":4},"sa":{"a":0,"k":0,"ix":5},"nm":"Transform"}],"nm":"Path","np":2,"cix":2,"bm":0,"ix":1,"mn":"ADBE Vector Group","hd":false}],"ip":90,"op":90,"st":0,"bm":0,"hidden":0},{"ddd":0,"ind":7,"ty":4,"nm":"Path","sr":1,"ks":{"o":{"a":0,"k":100,"ix":11},"r":{"a":0,"k":0,"ix":10},"p":{"a":0,"k":[153,166,0],"ix":2},"a":{"a":0,"k":[0,0,0],"ix":1},"s":{"a":0,"k":[100,100,100],"ix":6}},"ao":0,"shapes":[{"ty":"gr","it":[{"ind":0,"ty":"sh","ix":1,"ks":{"a":0,"k":{"i":[[-0.82,0],[0,-0.78],[4.8,0],[0,4.73],[-0.82,0],[0,-0.78],[-3.13,0],[0,3.18]],"o":[[0.82,0],[0,4.73],[-4.8,0],[0,-0.78],[0.82,0],[0,3.18],[3.13,0],[0,-0.78]],"v":[[7.183,-5],[8.663,-3.58],[0.003,5],[-8.667,-3.58],[-7.177,-5],[-5.697,-3.58],[0.003,2.16],[5.693,-3.58]],"c":true},"ix":2},"nm":"Path 1","mn":"ADBE Vector Shape - Group","hd":false},{"ty":"fl","c":{"a":0,"k":[0,0,0,1],"ix":4},"o":{"a":0,"k":100,"ix":5},"r":1,"bm":0,"nm":"Fill 1","mn":"ADBE Vector Graphic - Fill","hd":false},{"ty":"tr","p":{"a":0,"k":[0,0],"ix":2},"a":{"a":0,"k":[0,0],"ix":1},"s":{"a":0,"k":[300,300],"ix":3},"r":{"a":0,"k":0,"ix":6},"o":{"a":0,"k":100,"ix":7},"sk":{"a":0,"k":0,"ix":4},"sa":{"a":0,"k":0,"ix":5},"nm":"Transform"}],"nm":"Path","np":2,"cix":2,"bm":0,"ix":1,"mn":"ADBE Vector Group","hd":false}],"ip":90,"op":90,"st":0,"bm":0,"hidden":0},{"ddd":0,"ind":8,"ty":4,"nm":" Palka_Positiom 2","sr":1,"ks":{"o":{"a":0,"k":100,"ix":11},"r":{"a":0,"k":0,"ix":10},"p":{"a":1,"k":[{"i":{"x":0.667,"y":1},"o":{"x":0.333,"y":0},"t":0,"s":[150,64,0],"to":[0,0,0],"ti":[0,0,0]},{"i":{"x":0.667,"y":0.667},"o":{"x":0.333,"y":0.333},"t":30,"s":[150,227,0],"to":[0,0,0],"ti":[0,0,0]},{"i":{"x":0.667,"y":1},"o":{"x":0.333,"y":0},"t":32,"s":[150,227,0],"to":[0,0,0],"ti":[0,0,0]},{"t":60,"s":[150,63,0]}],"ix":2},"a":{"a":0,"k":[0,0,0],"ix":1},"s":{"a":0,"k":[100,100,100],"ix":6}},"ao":0,"shapes":[{"ty":"gr","it":[{"ty":"rc","d":1,"s":{"a":0,"k":[60,6],"ix":2},"p":{"a":0,"k":[0,0],"ix":3},"r":{"a":0,"k":3,"ix":4},"nm":"Rectangle Path 1","mn":"ADBE Vector Shape - Rect","hd":false},{"ty":"gf","o":{"a":0,"k":100,"ix":10},"r":1,"bm":0,"g":{"p":5,"k":{"a":0,"k":[0,0.031,0.918,0.643,0.152,0.016,0.861,0.822,0.304,0,0.804,1,0.652,0.292,0.467,1,1,0.584,0.129,1],"ix":9}},"s":{"a":0,"k":[0,-3],"ix":5},"e":{"a":0,"k":[0,3],"ix":6},"t":1,"nm":"Gradient Fill 1","mn":"ADBE Vector Graphic - G-Fill","hd":false},{"ty":"tr","p":{"a":0,"k":[0,0],"ix":2},"a":{"a":0,"k":[0,0],"ix":1},"s":{"a":0,"k":[300,300],"ix":3},"r":{"a":0,"k":0,"ix":6},"o":{"a":0,"k":100,"ix":7},"sk":{"a":0,"k":0,"ix":4},"sa":{"a":0,"k":0,"ix":5},"nm":"Transform"}],"nm":"Rectangle","np":2,"cix":2,"bm":0,"ix":1,"mn":"ADBE Vector Group","hd":false}],"ip":0,"op":90,"st":0,"bm":0},{"ddd":0,"ind":9,"ty":4,"nm":"Rectangle 3","td":1,"sr":1,"ks":{"o":{"a":1,"k":[{"i":{"x":[0.833],"y":[0.833]},"o":{"x":[0.167],"y":[0.167]},"t":29,"s":[70]},{"t":52,"s":[100]}],"ix":11},"r":{"a":0,"k":0,"ix":10},"p":{"a":0,"k":[153,147,0],"ix":2},"a":{"a":0,"k":[0,0,0],"ix":1},"s":{"a":0,"k":[100,100,100],"ix":6}},"ao":0,"shapes":[{"ty":"gr","it":[{"ty":"rc","d":1,"s":{"a":0,"k":[44,44],"ix":2},"p":{"a":0,"k":[0,0],"ix":3},"r":{"a":0,"k":10.593,"ix":4},"nm":"Rectangle Path 1","mn":"ADBE Vector Shape - Rect","hd":false},{"ty":"fl","c":{"a":0,"k":[1,1,1,1],"ix":4},"o":{"a":0,"k":100,"ix":5},"r":1,"bm":0,"nm":"Fill 1","mn":"ADBE Vector Graphic - Fill","hd":false},{"ty":"tr","p":{"a":0,"k":[0,0],"ix":2},"a":{"a":0,"k":[0,0],"ix":1},"s":{"a":0,"k":[300,300],"ix":3},"r":{"a":0,"k":0,"ix":6},"o":{"a":0,"k":100,"ix":7},"sk":{"a":0,"k":0,"ix":4},"sa":{"a":0,"k":0,"ix":5},"nm":"Transform"}],"nm":"Rectangle","np":2,"cix":2,"bm":0,"ix":1,"mn":"ADBE Vector Group","hd":false}],"ip":90,"op":90,"st":0,"bm":0,"hidden":0},{"ddd":0,"ind":10,"ty":4,"nm":"Rectangle 2","tt":1,"sr":1,"ks":{"o":{"a":0,"k":100,"ix":11},"r":{"a":0,"k":0,"ix":10},"p":{"a":0,"k":[153,213,0],"ix":2},"a":{"a":0,"k":[0,66,0],"ix":1},"s":{"a":1,"k":[{"i":{"x":[0.833,0.833,0.833],"y":[0.833,0.833,0.833]},"o":{"x":[0.167,0.167,0.167],"y":[0.167,0.167,0.167]},"t":32,"s":[100,100,100]},{"t":58,"s":[100,100,100]}],"ix":6}},"ao":0,"shapes":[{"ty":"gr","it":[{"ty":"rc","d":1,"s":{"a":0,"k":[44,44],"ix":2},"p":{"a":0,"k":[0,0],"ix":3},"r":{"a":0,"k":10.593,"ix":4},"nm":"Rectangle Path 1","mn":"ADBE Vector Shape - Rect","hd":false},{"ty":"fl","c":{"a":0,"k":[1,1,1,1],"ix":4},"o":{"a":0,"k":100,"ix":5},"r":1,"bm":0,"nm":"Fill 1","mn":"ADBE Vector Graphic - Fill","hd":false},{"ty":"tr","p":{"a":0,"k":[0,0],"ix":2},"a":{"a":0,"k":[0,0],"ix":1},"s":{"a":0,"k":[300,300],"ix":3},"r":{"a":0,"k":0,"ix":6},"o":{"a":0,"k":100,"ix":7},"sk":{"a":0,"k":0,"ix":4},"sa":{"a":0,"k":0,"ix":5},"nm":"Transform"}],"nm":"Rectangle","np":2,"cix":2,"bm":0,"ix":1,"mn":"ADBE Vector Group","hd":false}],"ip":90,"op":90,"st":0,"bm":0,"hidden":0},{"ddd":0,"ind":11,"ty":4,"nm":"Rectangle","sr":1,"ks":{"o":{"a":1,"k":[{"i":{"x":[0.833],"y":[0.833]},"o":{"x":[0.167],"y":[0.167]},"t":29,"s":[70]},{"t":52,"s":[100]}],"ix":11},"r":{"a":0,"k":0,"ix":10},"p":{"a":0,"k":[153,147,0],"ix":2},"a":{"a":0,"k":[0,0,0],"ix":1},"s":{"a":0,"k":[100,100,100],"ix":6}},"ao":0,"shapes":[{"ty":"gr","it":[{"ty":"rc","d":1,"s":{"a":0,"k":[44,44],"ix":2},"p":{"a":0,"k":[0,0],"ix":3},"r":{"a":0,"k":10.593,"ix":4},"nm":"Rectangle Path 1","mn":"ADBE Vector Shape - Rect","hd":false},{"ty":"fl","c":{"a":0,"k":[1,1,1,1],"ix":4},"o":{"a":0,"k":100,"ix":5},"r":1,"bm":0,"nm":"Fill 1","mn":"ADBE Vector Graphic - Fill","hd":false},{"ty":"tr","p":{"a":0,"k":[0,0],"ix":2},"a":{"a":0,"k":[0,0],"ix":1},"s":{"a":0,"k":[300,300],"ix":3},"r":{"a":0,"k":0,"ix":6},"o":{"a":0,"k":100,"ix":7},"sk":{"a":0,"k":0,"ix":4},"sa":{"a":0,"k":0,"ix":5},"nm":"Transform"}],"nm":"Rectangle","np":2,"cix":2,"bm":0,"ix":1,"mn":"ADBE Vector Group","hd":false}],"ip":90,"op":90,"st":0,"bm":0,"hidden":0},{"ddd":0,"ind":12,"ty":1,"nm":"Black Solid 1","sr":1,"ks":{"o":{"a":0,"k":100,"ix":11},"r":{"a":0,"k":0,"ix":10},"p":{"a":0,"k":[153,150,0],"ix":2},"a":{"a":0,"k":[153,150,0],"ix":1},"s":{"a":0,"k":[100,100,100],"ix":6}},"ao":0,"sw":306,"sh":300,"sc":"#000000","ip":90,"op":90,"st":0,"bm":0,"hidden":0}],"markers":[]}